{
  "GEN-CAN-001": {
    "service": "Generators",
    "subsystem": "Canopy",
    "steps": [
      {
        "check": "Measure airflow inside canopy",
        "threshold": "≥ 500 CFM",
        "tool": "Anemometer",
        "result": "Pass if airflow ≥ 500 CFM"
      },
      {
        "check": "Inspect louvers and ventilation fans",
        "threshold": "All fans operational",
        "tool": "Visual inspection",
        "result": "Pass if no obstruction"
      },
      {
        "action": "Install additional fans or redesign canopy",
        "verification": "Temperature inside canopy < 45°C under full load"
      }
    ]
  },
  "SOL-INV-101": {
    "service": "Solar",
    "subsystem": "Inverter",
    "steps": [
      {
        "check": "Measure DC bus voltage",
        "threshold": "≥ 48V",
        "tool": "Multimeter",
        "result": "Pass if voltage ≥ 48V"
      },
      {
        "check": "Check PV string configuration",
        "threshold": "Correct series/parallel arrangement",
        "tool": "String diagram",
        "result": "Pass if configuration matches design"
      },
      {
        "action": "Reconfigure strings or replace faulty inverter",
        "verification": "DC bus ≥ 48V under nominal irradiance"
      }
    ]
  },
  "HV-RET-301": {
    "service": "HighVoltage",
    "subsystem": "PowerLines",
    "steps": [
      {
        "check": "Measure line voltage at load end",
        "threshold": "≥ 95% of rated voltage",
        "tool": "Voltmeter",
        "result": "Pass if voltage drop ≤ 5%"
      },
      {
        "check": "Inspect cable size and length",
        "threshold": "Correct ampacity",
        "tool": "Cable datasheet",
        "result": "Pass if cable meets load requirements"
      },
      {
        "action": "Upgrade cable size or reduce line length",
        "verification": "Voltage drop ≤ 5% at rated load"
      }
    ]
  },
  "UPS-BAT-201": {
    "service": "UPS",
    "subsystem": "Battery",
    "steps": [
      {
        "check": "Check battery Ah rating",
        "threshold": "≥ design spec",
        "tool": "Battery tester",
        "result": "Pass if rating meets spec"
      },
      {
        "check": "Measure runtime under load",
        "threshold": "≥ 30 minutes",
        "tool": "Load bank",
        "result": "Pass if runtime ≥ 30 minutes"
      },
      {
        "action": "Replace degraded batteries, recalibrate charger",
        "verification": "Runtime ≥ 30 minutes at rated load"
      }
    ]
  },
  "PW-101": {
    "service": "PowerWizard",
    "subsystem": "Controller",
    "steps": [
      {
        "check": "Measure generator output voltage",
        "threshold": "±2% of rated",
        "tool": "Voltmeter",
        "result": "Pass if voltage within tolerance"
      },
      {
        "check": "Check AVR settings",
        "threshold": "Correct reference voltage",
        "tool": "AVR manual",
        "result": "Pass if settings match spec"
      },
      {
        "action": "Adjust AVR or replace faulty controller",
        "verification": "Voltage within ±2% of rated"
      }
    ]
  },
  "DSE-302": {
    "service": "DeepSea",
    "subsystem": "Controller",
    "steps": [
      {
        "check": "Measure battery voltage",
        "threshold": "≥ 12.5V",
        "tool": "Multimeter",
        "result": "Pass if voltage ≥ 12.5V"
      },
      {
        "check": "Check charger output",
        "threshold": "≥ 13.5V float",
        "tool": "Charger spec",
        "result": "Pass if charger delivers float voltage"
      },
      {
        "action": "Replace battery or repair charger",
        "verification": "Battery ≥ 12.5V under standby"
      }
    ]
  },
  "AC-COOL-101": {
    "service": "AC",
    "subsystem": "Cooling",
    "steps": [
      {
        "check": "Measure cooling load in BTU/hr",
        "threshold": "Within design capacity",
        "tool": "BTU meter",
        "result": "Pass if load ≤ rated capacity"
      },
      {
        "check": "Check refrigerant pressure",
        "threshold": "Within OEM spec",
        "tool": "Pressure gauge",
        "result": "Pass if pressure matches spec"
      },
      {
        "check": "Inspect condenser coils",
        "threshold": "Clean and unobstructed",
        "tool": "Visual inspection",
        "result": "Pass if coils are clean"
      },
      {
        "action": "Recharge refrigerant or upgrade cooling unit",
        "verification": "Ambient temperature maintained at 22–25°C"
      }
    ]
  },
  "MOT-REW-401": {
    "service": "MotorRewinding",
    "subsystem": "Stator",
    "steps": [
      {
        "check": "Compare winding turns per coil with OEM spec",
        "threshold": "Matches design",
        "tool": "Winding diagram",
        "result": "Pass if turns match spec"
      },
      {
        "check": "Measure resistance per phase",
        "threshold": "Balanced within ±5%",
        "tool": "Ohmmeter",
        "result": "Pass if resistance balanced"
      },
      {
        "check": "Inspect insulation class",
        "threshold": "Correct class rating",
        "tool": "Insulation tester",
        "result": "Pass if insulation meets spec"
      },
      {
        "action": "Rewind stator with correct turns and wire gauge",
        "verification": "Resistance balanced within ±5% across phases"
      }
    ]
  },
  "INC-CHM-101": {
    "service": "Incinerators",
    "subsystem": "Chamber",
    "steps": [
      {
        "check": "Measure chamber temperature",
        "threshold": "≥ 850°C",
        "tool": "Thermocouple",
        "result": "Pass if temperature ≥ 850°C"
      },
      {
        "check": "Check burner fuel supply",
        "threshold": "Stable fuel flow",
        "tool": "Flow meter",
        "result": "Pass if fuel supply stable"
      },
      {
        "check": "Inspect refractory lining",
        "threshold": "No cracks or wear",
        "tool": "Visual inspection",
        "result": "Pass if lining intact"
      },
      {
        "action": "Repair refractory or adjust burner fuel/air mix",
        "verification": "Chamber ≥ 850°C sustained"
      }
    ]
  },
  "CTRL-ATS-301": {
    "service": "Controls",
    "subsystem": "ATS",
    "steps": [
      {
        "check": "Check ATS control logic",
        "threshold": "Correct sequence",
        "tool": "PLC monitor",
        "result": "Pass if logic matches spec"
      },
      {
        "check": "Inspect contactors",
        "threshold": "Operational",
        "tool": "Visual inspection",
        "result": "Pass if contactors functional"
      },
      {
        "check": "Verify PLC interlocks",
        "threshold": "No faults",
        "tool": "PLC diagnostics",
        "result": "Pass if interlocks clear"
      },
      {
        "action": "Repair ATS logic or replace faulty contactors",
        "verification": "ATS transfers within 10 seconds of mains failure"
      }
    ]
  },
  "CTRL-RES-401": {
    "service": "Controls",
    "subsystem": "ReservoirAutomation",
    "steps": [
      {
        "check": "Measure diesel reservoir level",
        "threshold": "≥ 30%",
        "tool": "Level sensor",
        "result": "Pass if reservoir ≥ 30%"
      },
      {
        "check": "Check pump automation",
        "threshold": "Starts/stops correctly",
        "tool": "PLC monitor",
        "result": "Pass if automation works"
      },
      {
        "action": "Repair pump automation or recalibrate sensors",
        "verification": "Reservoir maintains ≥ 30% under load"
      }
    ]
  }
}
